ratschlab_common/__init__.py
ratschlab_common/dask_wrapper.py
ratschlab_common/spark_wrapper.py
ratschlab_common/utils.py
ratschlab_common/collections/__init__.py
ratschlab_common/collections/set_utils.py
ratschlab_common/db/__init__.py
ratschlab_common/db/dump_tables.py
ratschlab_common/db/utils.py
ratschlab_common/io/__init__.py
ratschlab_common/io/bigmatrix.py
ratschlab_common/io/dataframe_formats.py
ratschlab_common/io/sparse_df.py
ratschlab_common/io/chunks/__init__.py
ratschlab_common/io/chunks/chunk_indexing.py
ratschlab_common/io/chunks/repartition_dataframes.py
ratschlab_common/io/parquet_tools/__init__.py
ratschlab_common/io/parquet_tools/parquet_reader.py
ratschlab_common/io/parquet_tools/pq_tool.py
ratschlab_common/io/sql/__init__.py
ratschlab_common/scripts/__init__.py
ratschlab_common/scripts/bigmatrix_repack.py
ratschlab_common/scripts/export_db_to_files.py
tests/__init__.py
tests/conftest.py
tests/data/myhdf5file.h5
tests/data/numbers.txt
tests/db/__init__.py
tests/db/data_fixtures.py
tests/db/test_dump_tables.py
tests/io/__init__.py
tests/io/test_bigmatrix.py
tests/io/test_dataframe_formats.py
tests/io/test_sparse_df.py
tests/io/chunks/__init__.py
tests/io/chunks/test_chunk_indexing.py
tests/io/chunks/test_repartition_dataframes.py
tests/io/parquet_tools/__init__.py
tests/io/parquet_tools/test_pq_tool.py
tests/io/sql/__init__.py
tests/scripts/__init__.py
tests/scripts/test_bigmatrix_repack.py
tests/scripts/test_export_db_to_files.py
ratschlab_common-0.3.0.dist-info/LICENSE
ratschlab_common-0.3.0.dist-info/METADATA
ratschlab_common-0.3.0.dist-info/WHEEL
ratschlab_common-0.3.0.dist-info/entry_points.txt
ratschlab_common-0.3.0.dist-info/top_level.txt
ratschlab_common-0.3.0.dist-info/RECORD
