Metadata-Version: 2.1
Name: ratschlab-common
Version: 0.3.0
Summary: Small library of common functionalities used in various projects in the ratschlab
Home-page: https://github.com/ratschlab/ratschlab-common
Author: ETH Zurich, Biomedical Informatics Group
Author-email: marc.zimmermann@inf.ethz.ch
License: MIT license
Keywords: ratschlab_common
Platform: UNKNOWN
Classifier: Development Status :: 2 - Pre-Alpha
Classifier: Intended Audience :: Developers
Classifier: License :: OSI Approved :: MIT License
Classifier: Natural Language :: English
Classifier: Programming Language :: Python :: 3.5
Classifier: Programming Language :: Python :: 3.6
Requires-Dist: Click (>=7.0)
Requires-Dist: pyarrow (>=0.17.0)
Requires-Dist: pandas (>=1.0)
Requires-Dist: tables (>=3.4.2)
Requires-Dist: pgpasslib (>=1.1.0)
Requires-Dist: records (>=0.5)
Requires-Dist: scipy (>=1.4.0)
Requires-Dist: psycopg2-binary (>=2.7)
Provides-Extra: complete
Requires-Dist: dask[complete] (>=1.9.0) ; extra == 'complete'
Requires-Dist: distributed (>=1.22) ; extra == 'complete'
Requires-Dist: pyspark (>=2.4) ; extra == 'complete'
Provides-Extra: dask
Requires-Dist: dask[complete] (>=1.9.0) ; extra == 'dask'
Requires-Dist: distributed (>=1.22) ; extra == 'dask'
Provides-Extra: spark
Requires-Dist: pyspark (>=2.4) ; extra == 'spark'
